Metadata-Version: 2.4
Name: codecarbon
Version: 3.1.0
Author: Mila, DataForGood, BCG GAMMA, Comet.ml, Haverford College
License-Expression: MIT
Project-URL: Homepage, https://codecarbon.io/
Project-URL: Repository, https://github.com/mlco2/codecarbon
Project-URL: Dashboard, http://dashboard.codecarbon.io/
Project-URL: Documentation, https://mlco2.github.io/codecarbon/
Project-URL: Issues, https://github.com/mlco2/codecarbon/issues
Project-URL: Changelog, https://github.com/mlco2/codecarbon/releases
Classifier: Natural Language :: English
Classifier: Programming Language :: Python :: 3.7
Classifier: Programming Language :: Python :: 3.8
Classifier: Programming Language :: Python :: 3.9
Classifier: Programming Language :: Python :: 3.10
Classifier: Programming Language :: Python :: 3.11
Classifier: Programming Language :: Python :: 3.12
Classifier: Programming Language :: Python :: 3.13
Classifier: Programming Language :: Python :: 3.14
Requires-Python: >=3.7
License-File: LICENSE
Requires-Dist: arrow
Requires-Dist: click
Requires-Dist: fief-client[cli]
Requires-Dist: pandas>=2.3.3; python_version >= "3.14"
Requires-Dist: pandas; python_version < "3.14"
Requires-Dist: prometheus_client
Requires-Dist: psutil>=6.0.0
Requires-Dist: py-cpuinfo
Requires-Dist: pydantic
Requires-Dist: nvidia-ml-py
Requires-Dist: rapidfuzz
Requires-Dist: requests
Requires-Dist: questionary
Requires-Dist: rich
Requires-Dist: typer
Provides-Extra: viz-legacy
Requires-Dist: dash; extra == "viz-legacy"
Requires-Dist: dash_bootstrap_components>1.0.0; extra == "viz-legacy"
Requires-Dist: fire; extra == "viz-legacy"
Provides-Extra: viz
Requires-Dist: mock; extra == "viz"
Requires-Dist: pytest; extra == "viz"
Requires-Dist: responses; extra == "viz"
Requires-Dist: numpy<2.0.0; python_version < "3.9" and extra == "viz"
Requires-Dist: numpy; python_version >= "3.9" and extra == "viz"
Requires-Dist: psutil; extra == "viz"
Requires-Dist: requests-mock; extra == "viz"
Requires-Dist: rapidfuzz; extra == "viz"
Requires-Dist: importlib_resources; python_version < "3.9" and extra == "viz"
Provides-Extra: api
Requires-Dist: alembic<2.0.0; extra == "api"
Requires-Dist: bcrypt<5.0.0; extra == "api"
Requires-Dist: python-dateutil<3.0.0; extra == "api"
Requires-Dist: dependency-injector<5.0.0; extra == "api"
Requires-Dist: fastapi<1.0.0; extra == "api"
Requires-Dist: fief-client[fastapi]; extra == "api"
Requires-Dist: httpx; extra == "api"
Requires-Dist: pydantic[email]<2.0.0; extra == "api"
Requires-Dist: psycopg2-binary<3.0.0; extra == "api"
Requires-Dist: requests<3.0.0; extra == "api"
Requires-Dist: sqlalchemy<2.0.0; extra == "api"
Requires-Dist: uvicorn[standard]<1.0.0; extra == "api"
Requires-Dist: fastapi-pagination<1.0.0; extra == "api"
Requires-Dist: pytest; extra == "api"
Requires-Dist: mock; extra == "api"
Requires-Dist: responses; extra == "api"
Requires-Dist: numpy; extra == "api"
Requires-Dist: psutil; extra == "api"
Requires-Dist: requests-mock; extra == "api"
Requires-Dist: rapidfuzz; extra == "api"
Requires-Dist: PyJWT; extra == "api"
Requires-Dist: logfire[fastapi]>=1.0.1; extra == "api"
Dynamic: license-file
